text_util_en_pt/__init__.py
text_util_en_pt/cleaner.py
text_util_en_pt-1.0.7.dist-info/LICENSE
text_util_en_pt-1.0.7.dist-info/METADATA
text_util_en_pt-1.0.7.dist-info/WHEEL
text_util_en_pt-1.0.7.dist-info/top_level.txt
text_util_en_pt-1.0.7.dist-info/RECORD
