Metadata-Version: 2.1
Name: text-util-en-pt
Version: 1.0.7
Summary: Python project for text cleaning. Some specifics for English and Portuguese languages.
Author: Carlo Moro
Author-email: Carlo Moro <cnmoro@gmail.com>
Project-URL: Homepage, https://github.com/cnmoro
Project-URL: Bug Tracker, https://github.com/cnmoro
Classifier: Programming Language :: Python :: 3
Classifier: License :: OSI Approved :: MIT License
Classifier: Operating System :: OS Independent
Requires-Python: >=3.7
License-File: LICENSE
Requires-Dist: langdetect
